supaconify/__init__.py
supaconify/_version.py
supaconify/cli.py
supaconify/client.py
supaconify/message.py
supaconify-0.0.2.dist-info/METADATA
supaconify-0.0.2.dist-info/WHEEL
supaconify-0.0.2.dist-info/entry_points.txt
supaconify-0.0.2.dist-info/top_level.txt
supaconify-0.0.2.dist-info/RECORD
